{"get": "fixtures/headtohead", "parameters": {"h2h": "39-1359"}, "errors": [], "results": 4, "paging": {"current": 1, "total": 1}, "response": [{"fixture": {"id": 451024, "referee": null, "timezone": "UTC", "date": "2013-01-05T15:00:00+00:00", "timestamp": 1357398000, "periods": {"first": 1357398000, "second": 1357401600}, "venue": {"id": null, "name": "Kenilworth Road Stadium", "city": null}, "status": {"long": "Match Finished", "short": "FT", "elapsed": 90, "extra": null}}, "league": {"id": 45, "name": "FA Cup", "country": "England", "logo": "https://media.api-sports.io/football/leagues/45.png", "flag": "https://media.api-sports.io/flags/gb-eng.svg", "season": 2012, "round": "3rd Round", "standings": false}, "teams": {"home": {"id": 1359, "name": "Luton", "logo": "https://media.api-sports.io/football/teams/1359.png", "winner": true}, "away": {"id": 39, "name": "Wolves", "logo": "https://media.api-sports.io/football/teams/39.png", "winner": false}}, "goals": {"home": 1, "away": 0}, "score": {"halftime": {"home": 0, "away": 0}, "fulltime": {"home": 1, "away": 0}, "extratime": {"home": null, "away": null}, "penalty": {"home": null, "away": null}}}, {"fixture": {"id": 1035094, "referee": "J. Smith", "timezone": "UTC", "date": "2023-09-23T14:00:00+00:00", "timestamp": 1695477600, "periods": {"first": 1695477600, "second": 1695481200}, "venue": {"id": 551, "name": "Kenilworth Road", "city": "Luton, Bedfordshire"}, "status": {"long": "Match Finished", "short": "FT", "elapsed": 90, "extra": null}}, "league": {"id": 39, "name": "Premier League", "country": "England", "logo": "https://media.api-sports.io/football/leagues/39.png", "flag": "https://media.api-sports.io/flags/gb-eng.svg", "season": 2023, "round": "Regular Season - 6", "standings": true}, "teams": {"home": {"id": 1359, "name": "Luton", "logo": "https://media.api-sports.io/football/teams/1359.png", "winner": null}, "away": {"id": 39, "name": "Wolves", "logo": "https://media.api-sports.io/football/teams/39.png", "winner": null}}, "goals": {"home": 1, "away": 1}, "score": {"halftime": {"home": 0, "away": 0}, "fulltime": {"home": 1, "away": 1}, "extratime": {"home": null, "away": null}, "penalty": {"home": null, "away": null}}}, {"fixture": {"id": 1035523, "referee": "D. Coote", "timezone": "UTC", "date": "2024-04-27T14:00:00+00:00", "timestamp": 1714226400, "periods": {"first": 1714226400, "second": 1714230000}, "venue": {"id": 600, "name": "Molineux Stadium", "city": "Wolverhampton, West Midlands"}, "status": {"long": "Match Finished", "short": "FT", "elapsed": 90, "extra": null}}, "league": {"id": 39, "name": "Premier League", "country": "England", "logo": "https://media.api-sports.io/football/leagues/39.png", "flag": "https://media.api-sports.io/flags/gb-eng.svg", "season": 2023, "round": "Regular Season - 35", "standings": true}, "teams": {"home": {"id": 39, "name": "Wolves", "logo": "https://media.api-sports.io/football/teams/39.png", "winner": true}, "away": {"id": 1359, "name": "Luton", "logo": "https://media.api-sports.io/football/teams/1359.png", "winner": false}}, "goals": {"home": 2, "away": 1}, "score": {"halftime": {"home": 1, "away": 0}, "fulltime": {"home": 2, "away": 1}, "extratime": {"home": null, "away": null}, "penalty": {"home": null, "away": null}}}, {"fixture": {"id": 1064405, "referee": null, "timezone": "UTC", "date": "2023-08-02T18:30:00+00:00", "timestamp": 1691001000, "periods": {"first": 1691001000, "second": 1691004600}, "venue": {"id": 600, "name": "Molineux Stadium", "city": "Wolverhampton, West Midlands"}, "status": {"long": "Match Finished", "short": "FT", "elapsed": 90, "extra": null}}, "league": {"id": 667, "name": "Friendlies Clubs", "country": "World", "logo": "https://media.api-sports.io/football/leagues/667.png", "flag": null, "season": 2023, "round": "Club Friendlies 3", "standings": false}, "teams": {"home": {"id": 39, "name": "Wolves", "logo": "https://media.api-sports.io/football/teams/39.png", "winner": null}, "away": {"id": 1359, "name": "Luton", "logo": "https://media.api-sports.io/football/teams/1359.png", "winner": null}}, "goals": {"home": 0, "away": 0}, "score": {"halftime": {"home": 0, "away": 0}, "fulltime": {"home": 0, "away": 0}, "extratime": {"home": null, "away": null}, "penalty": {"home": null, "away": null}}}]}